[
  {
    "data": "02/02/2025",
    "integrantes": [
      4,
      7,
      8,
      2,
      6,
      13,
      1,
      11
    ],
    "musicas": [
      47,
      41,
      42
    ],
    "header": [
      4,
      7,
      8
    ]
  },
  {
    "data": "09/02/2025",
    "integrantes": [
      9,
      5,
      15,
      3,
      12,
      13,
      1,
      11
    ],
    "musicas": [
      51,
      9,
      8
    ],
    "header": [
      9,
      5
    ]
  },
  {
    "data": "16/02/2025",
    "integrantes": [
      4,
      9,
      14,
      2,
      6,
      12,
      1,
      11
    ],
    "musicas": [
      36,
      48
    ],
    "header": [
      4,
      9,
      14
    ]
  },
  {
    "data": "23/02/2025",
    "integrantes": [
      7,
      8,
      15,
      3,
      6,
      2,
      1,
      11
    ],
    "musicas": [
      7,
      30,
      14
    ],
    "header": [
      7,
      8
    ]
  },
  {
    "data": "02/03/2025",
    "integrantes": [
      9,
      8,
      15,
      3,
      6,
      16,
      11
    ],
    "musicas": [
      15
    ],
    "header": [
      9,
      8
    ]
  },
  {
    "data": "09/03/2025",
    "integrantes": [
      7,
      4,
      14,
      3,
      12,
      13,
      1,
      11
    ],
    "musicas": [
      50,
      1,
      21
    ],
    "header": [
      7,
      4,
      14
    ]
  },
  {
    "data": "16/03/2025",
    "integrantes": [
      9,
      5,
      2,
      6,
      13,
      16
    ],
    "musicas": [
      31
    ],
    "header": [
      9,
      5
    ]
  },
  {
    "data": "23/03/2025",
    "integrantes": [
      4,
      8,
      14,
      2,
      12,
      13,
      1,
      11
    ],
    "musicas": [
      24,
      35
    ],
    "header": [
      4,
      8,
      14
    ]
  },
  {
    "data": "30/03/2025",
    "integrantes": [
      7,
      5,
      15,
      3,
      12,
      2,
      1
    ],
    "musicas": [
      26,
      34
    ],
    "header": [
      7,
      5
    ]
  },
  {
    "data": "06/04/2025",
    "integrantes": [
      4,
      5,
      14,
      2,
      6,
      12,
      1
    ],
    "musicas": [
      52,
      41,
      3
    ],
    "header": [
      4,
      5,
      14
    ]
  },
  {
    "data": "13/04/2025",
    "integrantes": [
      9,
      8,
      15,
      3,
      6,
      2,
      1,
      11
    ],
    "musicas": [
        19,
      9,
      33
        ],
    "header": [
      9,
      8
    ]
  },
  {
    "data": "20/04/2025",
    "integrantes": [
      7,
      9,
      3,
      2,
      12,
      13,
      1,
      11
    ],
    "musicas": [
      35
    ],
    "header": [
      7,
      9
    ]
  },
  {
    "data": "27/04/2025",
    "integrantes": [
      5,
      8,
      15,
      2,
      12,
      13,
      17
    ],
    "musicas": [
      2,
      37,
      13
    ],
    "header": [
      5,
      8
    ]
  },
  {
    "data": "04/05/2025",
    "integrantes": [
      9,
      8,
      15,
      3,
      12,
      13,
      1
    ],
    "musicas": [
      21,
      8,
      48
    ],
    "header": [
      9,
      8
    ]
  },
  {
    "data": "11/05/2025",
    "integrantes": [
      4,
      5,
      14,
      3,
      6,
      2,
      1,
      11
    ],
    "musicas": [
      18,
      51,
      29
    ],
    "header": [
      4,
      5,
      14
    ]
  },
  {
    "data": "18/05/2025",
    "integrantes": [
      9,
      8,
      14,
      2,
      6,
      12,
      16,
      11
    ],
    "musicas": [
      32,
      5
    ],
    "header": [
      9,
      8,
      14
    ]
  },
  {
    "data": "25/05/2025",
    "integrantes": [
      7,
      8,
      15,
      3,
      12,
      2,
      16
    ],
    "musicas": [
      14,
      31,
      7
    ],
    "header": [
      7,
      8
    ]
  },
  {
    "data": "01/06/2025",
    "integrantes": [
      7,
      8,
      15,
      13,
      12,
      2,
      16
    ],
    "musicas": [
      17,
      30
    ],
    "header": [
      7,
      8
    ]
  },
  {
    "data": "08/06/2025",
    "integrantes": [
      4,
      9,
      14,
      13,
      12,
      3,
      1,
      11
    ],
    "musicas": [
      41,
      28,
      33
    ],
    "header": [
      4,
      9,
      14
    ]
  },
  {
    "data": "15/06/2025",
    "integrantes": [
      4,
      8,
      14,
      13,
      12,
      2,
      1,
      11
    ],
    "musicas": [
      12,
      46,
      24
    ],
    "header": [
      4,
      8,
      14
    ]
  },
  {
    "data": "22/06/2025",
    "integrantes": [
      9,
      8,
      15,
      2,
      6,
      3,
      17,
      11
    ],
    "musicas": [
      10,
      52,
      63
    ],
    "header": [
      9,
      8
    ]
  },
  {
    "data": "29/06/2025",
    "integrantes": [
      9,
      7,
      15,
      2,
      6,
      3,
      1,
      11
    ],
    "musicas": [
      47,
      64,
      62
    ],
    "header": [
      9,
      7
    ]
  },
  {
    "data": "06/07/2025",
    "integrantes": [
      4,
      14,
      8,
      2,
      6,
      3,
      17,
      11
    ],
    "musicas": [
      6,
      59,
      25
    ],
    "header": [
      4,
      14,
      8
    ]
  },
  {
    "data": "13/07/2025",
    "integrantes": [
      9,
      14,
      8,
      13,
      12,
      3,
      16,
      11
    ],
    "musicas": [
        38,35,9
    ],
    "header": [
      9,
      14,
      8
    ]
  },
  {
    "data": "20/07/2025",
    "integrantes": [
      9,
      4,
      5,
      13,
      12,
      2,
      16
    ],
    "musicas": [
      53,
      45
    ],
    "header": [
      9,
      4,
      5
    ]
  },
  {
    "data": "27/07/2025",
    "integrantes": [
      7,
      14,
      15,
      13,
      12,
      2,
      16,
      11
    ],
    "header": [
      7,
      2
    ],
    "musicas": [
      57,
      13
    ]
  },
  {
    "data": "03/08/2025",
    "integrantes": [
      9,
      14,
      15,
      2,
      6,
      3,
      17,
      11
    ],
    "header": [
      9,
      2
    ],
    "musicas": [
      11,
      21,
      8
    ]
  },
  {
    "data": "10/08/2025",
    "integrantes": [
      7,
      14,
      15,
      2,
      6,
      3,
      1,
      11
    ],
    "header": [
      7,
      1
    ],
    "musicas": [
      18,
      51,
      23
    ]
  },
  {
    "data": "17/08/2025",
    "integrantes": [
      9,
      8,
      5,
      2,
      12,
      3,
      16,
      11
    ],
    "header": [
      9,
      12
    ],
    "musicas": [
      5,
      37
    ]
  },
  {
    "data": "24/08/2025",
    "integrantes": [
      4,
      8,
      5,
      13,
      6,
      2,
      1,
      11
    ],
    "header": [
      4,
      2
    ],
    "musicas": [
      56,
      43,
      3
    ]
  },
  {
    "data": "31/08/2025",
    "integrantes": [
      4,
      9,
      5,
      13,
      12,
      2,
      16
    ],
    "header": [
      4,
      13
    ],
    "musicas": [
      60,
      40,
      20
    ]
  },
  {
    "data": "07/09/2025",
    "integrantes": [
      7,
      14,
      15,
      13,
      12,
      3,
      1,
      11
    ],
    "header": [
      7,
      13
    ],
    "musicas": [
      16,
      52,
      64
    ]
  },
  {
    "data": "14/09/2025",
    "integrantes": [
      4,
      9,
      5,
      2,
      6,
      3,
      1,
      11
    ],
    "header": [
      2
    ],
    "musicas": [
      22,
      50,
      58,
      38
    ]
  },
  {
    "data": "21/09/2025",
    "integrantes": [
      9,
      14,
      8,
      2,
      6,
      1
    ],
    "header": [
      9,
      2
    ],
    "musicas": [
      7,
      32,
      63,
      13
    ]
  },
  {
    "data": "28/09/2025",
    "integrantes": [
      4,
      5,
      8,
      2,
      6,
      3,
      1,
      11
    ],
    "header": [
      9,
      2
    ],
    "musicas": [
      53
    ]
  },
  {
    "data": "05/10/2025",
    "integrantes": [
      4,
      5,
      8,
      13,
      12,
      3,
      17,
      11
    ],
    "header": [
      4,
      12
    ],
    "musicas": [
      10,
      59,
      17
    ]
  },
  {
    "data": "12/10/2025",
    "integrantes": [
      7,
      14,
      15,
      13,
      12,
      3,
      16,
      11
    ],
    "header": [
      7,
      13
    ],
    "musicas": [
      47,
      57,
      12
    ]
  },
  {
    "data": "19/10/2025",
    "integrantes": [
      4,
      5,
      8,
      13,
      12,
      2,
      1,
      18
    ],
    "header": [
      4,
      2
    ],
    "musicas": [
      6,
      55,
      33
    ]
  },
  {
    "data": "26/10/2025",
    "integrantes": [
      9,
      14,
      15,
      2,
      6,
      3,
      16,
      11
    ],
    "header": [
      9,
      1
    ],
    "musicas": [
      42,
      25,
      28
    ]
  },
  {
    "data": "02/11/2025",
    "integrantes": [
      4,
      5,
      8,
      2,
      6,
      3,
      1,
      11
    ],
    "header": [
      4,
      2
    ],
    "musicas": [
      30,
      3,
      61
    ]
  },
  {
    "data": "09/11/2025",
    "integrantes": [
      9,
      14,
      8,
      2,
      6,
      3,
      1,
      18,
      11
    ],
    "header": [
      9,
      1
    ],
    "musicas": [
      35,
      9,
      21,
      8
    ]
  },
  {
    "data": "16/11/2025",
    "integrantes": [
      7,
      5,
      15,
      13,
      12,
      2,
      16
    ],
    "header": [
      7,
      12
    ],
    "musicas": [
      34,
      5,
      62
    ]
  },
  {
    "data": "23/11/2025",
    "integrantes": [
      4,
      14,
      8,
      13,
      6,
      2,
      1,
      18
    ],
    "header": [
      4,
      2
    ],
    "musicas": [
      3,
      25,
      43
    ]
  },
  {
    "data": "30/11/2025",
    "integrantes": [
      7,
      14,
      15,
      13,
      12,
      3,
      17,
      11
    ],
    "header": [
      7,
      13
    ],
    "musicas": [
      60,
      40,
      20
    ]
  },
  {
    "data": "07/12/2025",
    "integrantes": [
      9,
      5,
      15,
      2,
      6,
      3,
      16
    ],
    "header": [
      9,
      2
    ],
    "musicas": [
      22,
      50,
      58
    ]
  },
  {
    "data": "14/12/2025",
    "integrantes": [
      7,
      4,
      8,
      2,
      6,
      3,
      1,
      11
    ],
    "header": [
      7,
      2
    ],
    "musicas": [
      19,
      29,
      18,
      51
    ]
  },
  {
    "data": "21/12/2025",
    "integrantes": [
      4,
      14,
      5,
      2,
      6,
      3,
      1,
      18
    ],
    "header": [
      4,
      1
    ],
    "musicas": [
      39,
      46,
      72
    ],
    "faltas": [
      4
    ]
  },
  {
    "data": "25/12/2025",
    "integrantes": [
      9,
      4,
      14,
      13,
      6,
      2,
      1,
      11
    ],
    "header": [
      9,
      2
    ],
    "musicas": [
      45,
      73,
      68,
      33,
      17
    ],
    "faltas": [
      4
    ]
  },
  {
    "data": "28/12/2025",
    "integrantes": [
      9,
      14,
      15,
      13,
      12,
      3,
      17,
      18
    ],
    "header": [
      9,
      13
    ],
    "musicas": [
      32,
      13,
      2
    ]
  },
  {
    "data": "31/12/2025",
    "integrantes": [
      9,
      4,
      8,
      13,
      12,
      3,
      1,
      11
    ],
    "header": [
      4,
      12
    ],
    "musicas": [
      12,
      69,
      61
    ]
  },
  {
    "data": "04/01/2026",
    "integrantes": [
      9,
      5,
      15,
      13,
      12,
      2,
      1,
      11
    ],
    "header": [
      9,
      12
    ],
    "musicas": [
      10,
      57,
      30
    ]
  },
  {
    "data": "11/01/2026",
    "integrantes": [
      4,
      14,
      8,
      2,
      12,
      3,
      1,
      18
    ],
    "header": [
      4,
      2
    ],
    "musicas": [
      53,
      7,
      37
    ]
  },
  {
    "data": "18/01/2026",
    "integrantes": [
      4,
      9,
      8,
      2,
      6,
      3,
      17,
      11
    ],
    "header": [
      17
    ],
    "musicas": [
      47,17,71
    ]
  },
  {
    "data": "25/01/2026",
    "integrantes": [
      9,
      14,
      15,
      2,
      6,
      3,
      16,
      18
    ],
    "header": [
      14
    ],
    "musicas": [
      6,
      24,
      28
    ]
  },

  {
    "data": "01/02/2026",
    "integrantes": [4,9,8,2,6,3,1,11],
    "header": [6],
    "musicas": []
  },
  {
    "data": "08/02/2026",
    "integrantes": [9,5,15,13,12,3,1,18],
    "header": [9,12],
    "musicas": []
  },
  {
    "data": "15/02/2026",
    "integrantes": [4,14,8,13,12,3,16,11],
    "header": [4,13],
    "musicas": []
  },
  {
    "data": "22/02/2026",
    "integrantes": [9,14,15,13,12,2,17,18],
    "header": [15],
    "musicas": []
  }

]